devicetree/__init__.py
devicetree/dtlib.py
devicetree/edtlib.py
devicetree/grutils.py
devicetree-0.0.2.dist-info/METADATA
devicetree-0.0.2.dist-info/WHEEL
devicetree-0.0.2.dist-info/top_level.txt
devicetree-0.0.2.dist-info/RECORD
